amqpworker/__init__.py
amqpworker/app.py
amqpworker/bucket.py
amqpworker/conf.py
amqpworker/connections.py
amqpworker/consumer.py
amqpworker/decorators.py
amqpworker/easyqueue/__init__.py
amqpworker/easyqueue/connection.py
amqpworker/easyqueue/exceptions.py
amqpworker/easyqueue/message.py
amqpworker/easyqueue/queue.py
amqpworker/entrypoints.py
amqpworker/exceptions.py
amqpworker/options.py
amqpworker/rabbitmq/__init__.py
amqpworker/rabbitmq/entrypoints.py
amqpworker/rabbitmq/message.py
amqpworker/routes.py
amqpworker/scheduled/__init__.py
amqpworker/signals/__init__.py
amqpworker/signals/base.py
amqpworker/signals/handlers/__init__.py
amqpworker/signals/handlers/base.py
amqpworker/signals/handlers/rabbitmq.py
amqpworker/types/__init__.py
amqpworker/types/registry.py
amqpworker/typing/__init__.py
amqpworker/utils.py
amqp_workers-0.1.5.dist-info/LICENSE
amqp_workers-0.1.5.dist-info/METADATA
amqp_workers-0.1.5.dist-info/WHEEL
amqp_workers-0.1.5.dist-info/RECORD
