Metadata-Version: 2.1
Name: amqp-workers
Version: 0.1.5
Summary: amqp-worker is a Python-based multi-threaded RabbitMQ consumer framework
Home-page: https://git.loom.run/Coder/amqp-worker
License: MIT
Keywords: amqp,rabbitmq
Author: JimZhang
Author-email: zzl22100048@gmail.com
Requires-Python: >=3.8,<4.0
Classifier: License :: OSI Approved :: MIT License
Classifier: Programming Language :: Python :: 3
Classifier: Programming Language :: Python :: 3.8
Classifier: Programming Language :: Python :: 3.9
Classifier: Programming Language :: Python :: 3.10
Classifier: Programming Language :: Python :: 3.11
Requires-Dist: amqpstorm (>=2.10.6,<3.0.0)
Requires-Dist: cached-property (>=1.5.2,<2.0.0)
Requires-Dist: delayedqueue (>=1.0.0,<2.0.0)
Requires-Dist: loguru (>=0.7.0,<0.8.0)
Requires-Dist: orjson (>=3.9.10,<4.0.0)
Requires-Dist: pydantic (==1.10.7)
Project-URL: Repository, https://git.loom.run/Coder/amqp-worker
